numerai/__init__.py
numerai/_modidx.py
numerai/core.py
numerai/data.py
numerai/download.py
numerai/utils.py
numerain/__init__.py
numerain/_modidx.py
numerain/core.py
numerain/data.py
numerain/download.py
numerain/utils.py
numerain-0.0.1.dist-info/LICENSE
numerain-0.0.1.dist-info/LICENSE.md
numerain-0.0.1.dist-info/METADATA
numerain-0.0.1.dist-info/WHEEL
numerain-0.0.1.dist-info/entry_points.txt
numerain-0.0.1.dist-info/top_level.txt
numerain-0.0.1.dist-info/RECORD
