Metadata-Version: 2.1
Name: numerain
Version: 0.0.1
Summary: Main repo for experimental model building which are used in numer.ai tournament
Home-page: https://github.com/bigcube-ai/numerain/
Author: Synth
Author-email: synth@bigcube.ai
License: Apache Software License 2.0
Keywords: nbdev numerain
Classifier: Development Status :: 3 - Alpha
Classifier: Intended Audience :: Developers
Classifier: Natural Language :: English
Classifier: Programming Language :: Python :: 3.7
Classifier: Programming Language :: Python :: 3.8
Classifier: Programming Language :: Python :: 3.9
Classifier: Programming Language :: Python :: 3.10
Classifier: License :: OSI Approved :: Apache Software License
Requires-Python: >=3.7
License-File: LICENSE
License-File: LICENSE.md
Requires-Dist: pandas
Requires-Dist: numerapi
Requires-Dist: numpy
Requires-Dist: scipy
Requires-Dist: halo
Provides-Extra: dev
